smtp4dev/__init__.py
smtp4dev/message.py
smtp4dev/smtp4dev.py
smtp4dev-0.1.4.dist-info/LICENSE
smtp4dev-0.1.4.dist-info/WHEEL
smtp4dev-0.1.4.dist-info/METADATA
smtp4dev-0.1.4.dist-info/RECORD
