Metadata-Version: 2.1
Name: smtp4dev
Version: 0.1.4
Summary: Provides access to emails caught by the SMTP4dev development server
Author: Guillaume Pasquet
Author-email: guillaume.pasquet@plentific.com
Requires-Python: >=3.6
Classifier: Programming Language :: Python :: 3
Classifier: Programming Language :: Python :: 3.6
Classifier: Programming Language :: Python :: 3.7
Classifier: Programming Language :: Python :: 3.8
Requires-Dist: requests (>=2.23.0,<3.0.0)
